{
  "index": {
    "group": [
      {
        "name": "Toc",
        "group": [
          {
            "name": "1. Introduzione",
            "subtitle": "Ambientazione tematica",
            "link": [
              {
                "label": "Introduzione",
                "target": "b74749"
              },
              {
                "label": "Dramatis personae",
                "target": "b74749"
              }
            ]
          },
          {
            "name": "2. Studio generale",
            "subtitle": "Vicende storiche dell’editoria musicale ticinese durante il\n                  Risorgimento: un sommario\n            ",
            "link": [
              {
                "label": "Retroscena ",
                "target": "8c26be",
                "chapter": "02"
              },
              {
                "label": "Realtà complementari ",
                "target": "b8b040",
                "chapter": "02"
              },
              {
                "label": "Attività di frontiera ",
                "target": "b31a99",
                "chapter": "02"
              },
              {
                "label": "Contraffattori e contrabbandieri ",
                "target": "952f7e",
                "chapter": "02"
              },
              {
                "label": "Reagisce lo Stato ",
                "target": "e980f3",
                "chapter": "02"
              },
              {
                "label": "Lista bianca – lista nera ",
                "target": "516b92",
                "chapter": "02"
              },
              {
                "label": "Strategie di conversione ",
                "target": "37cd33",
                "chapter": "02"
              },
              {
                "label": "Convenzioni inconvenienti ",
                "target": "4e4fa4",
                "chapter": "02"
              },
              {
                "label": "Epilogo ",
                "target": "4f5baa",
                "chapter": "02"
              }
            ]
          },
          {
            "name": "3. Cronologia",
            "subtitle": "Sunto cronologico dei principali avvenimenti legati alla storia e allo sviluppo dell’editoria\n            musicale ticinese durante il Risorgimento e oltre (1808–1902)",
            "link": "fd0e0f"
          },
          {
            "name": "4. Carteggio",
            "subtitle": "Lettere di corrispondenza di vari attori legati agli eventi\n                  (1826–1863): trascrizione con commento critico",
            "link": [
              {
                "label": "Carteggio.1826.1 ",
                "target": "34d3db",
                "chapter": "04"
              },
              {
                "label": "Carteggio.1826.2 ",
                "target": "ee0e19",
                "chapter": "04"
              },
              {
                "label": "Carteggio.1827.1 ",
                "target": "88814f",
                "chapter": "04"
              },
              {
                "label": "Carteggio.1828.1 ",
                "target": "730e59",
                "chapter": "04"
              },
              {
                "label": "Carteggio.1828.2 ",
                "target": "e3e2b2",
                "chapter": "04"
              },
              {
                "label": "Carteggio.1831.1 ",
                "target": "7bcd85",
                "chapter": "04"
              },
              {
                "label": "Carteggio.1831.2 ",
                "target": "7ed109",
                "chapter": "04"
              },
              {
                "label": "Carteggio.1832.1 ",
                "target": "927e6d",
                "chapter": "04"
              },
              {
                "label": "Carteggio.1832.2 ",
                "target": "668714",
                "chapter": "04"
              },
              {
                "label": "Carteggio.1833.1 ",
                "target": "06a80c",
                "chapter": "04"
              },
              {
                "label": "Carteggio.1833.2 ",
                "target": "ef3918",
                "chapter": "04"
              },
              {
                "label": "Carteggio.1833.3 ",
                "target": "b9fd00",
                "chapter": "04"
              },
              {
                "label": "Carteggio.1835.1 ",
                "target": "517ae0",
                "chapter": "04"
              },
              {
                "label": "Carteggio.1835.2 ",
                "target": "086c6d",
                "chapter": "04"
              },
              {
                "label": "Carteggio.1835.3 ",
                "target": "78f664",
                "chapter": "04"
              },
              {
                "label": "Carteggio.1836.1 ",
                "target": "517c59",
                "chapter": "04"
              },
              {
                "label": "Carteggio.1836.2 ",
                "target": "cfc341",
                "chapter": "04"
              },
              {
                "label": "Carteggio.1836.3",
                "target": "7353ea",
                "chapter": "04"
              },
              {
                "label": "Carteggio.1836.4",
                "target": "f21c98",
                "chapter": "04"
              },
              {
                "label": "Carteggio.1836.5 ",
                "target": "4a04d1",
                "chapter": "04"
              },
              {
                "label": "Carteggio.1836.6 ",
                "target": "914c8a",
                "chapter": "04"
              },
              {
                "label": "Carteggio.1836.7 ",
                "target": "c1b21f",
                "chapter": "04"
              },
              {
                "label": "Carteggio.1836.8 ",
                "target": "885dcb",
                "chapter": "04"
              },
              {
                "label": "Carteggio.1836.9 ",
                "target": "876f45",
                "chapter": "04"
              },
              {
                "label": "Carteggio.1836.10 ",
                "target": "409440",
                "chapter": "04"
              },
              {
                "label": "Carteggio.1837.1 ",
                "target": "31dba1",
                "chapter": "04"
              },
              {
                "label": "Carteggio.1837.2 ",
                "target": "75be59",
                "chapter": "04"
              },
              {
                "label": "Carteggio.1838.1 ",
                "target": "f41ba9",
                "chapter": "04"
              },
              {
                "label": "Carteggio.1838.2 ",
                "target": "211ea9",
                "chapter": "04"
              },
              {
                "label": "Carteggio.1838.3 ",
                "target": "686e14",
                "chapter": "04"
              },
              {
                "label": "Carteggio.1841.2 ",
                "target": "c8d0f1",
                "chapter": "04"
              },
              {
                "label": "Carteggio.1841.3 ",
                "target": "35064a",
                "chapter": "04"
              },
              {
                "label": "Carteggio.1842.1 ",
                "target": "d376a7",
                "chapter": "04"
              },
              {
                "label": "Carteggio.1842.2 ",
                "target": "45678b",
                "chapter": "04"
              },
              {
                "label": "Carteggio.1842.3 ",
                "target": "577537",
                "chapter": "04"
              },
              {
                "label": "Carteggio.1843.1 ",
                "target": "85eb92",
                "chapter": "04"
              },
              {
                "label": "Carteggio.1843.2 ",
                "target": "9fd98c",
                "chapter": "04"
              },
              {
                "label": "Carteggio.1843.3 ",
                "target": "ea6ac4",
                "chapter": "04"
              },
              {
                "label": "Carteggio.1844.1 ",
                "target": "6d124d",
                "chapter": "04"
              },
              {
                "label": "Carteggio.1844.2 ",
                "target": "9f8aa5",
                "chapter": "04"
              },
              {
                "label": "Carteggio.1844.3 ",
                "target": "d3ef07",
                "chapter": "04"
              },
              {
                "label": "Carteggio.1844.4 ",
                "target": "900e9c",
                "chapter": "04"
              },
              {
                "label": "Carteggio.1844.5 ",
                "target": "376cbc",
                "chapter": "04"
              },
              {
                "label": "Carteggio.1847.1 ",
                "target": "495094",
                "chapter": "04"
              },
              {
                "label": "Carteggio.1848.1 ",
                "target": "587f5c",
                "chapter": "04"
              },
              {
                "label": "Carteggio.1848.2 ",
                "target": "818f18",
                "chapter": "04"
              },
              {
                "label": "Carteggio.1849.1 ",
                "target": "5db204",
                "chapter": "04"
              },
              {
                "label": "Carteggio.1849.2 ",
                "target": "6b6bd3",
                "chapter": "04"
              },
              {
                "label": "Carteggio.1849.3 ",
                "target": "339a9e",
                "chapter": "04"
              },
              {
                "label": "Carteggio.1849.4 ",
                "target": "2e9174",
                "chapter": "04"
              },
              {
                "label": "Carteggio.1849.5 ",
                "target": "e484ce",
                "chapter": "04"
              },
              {
                "label": "Carteggio.1850.1 ",
                "target": "25c363",
                "chapter": "04"
              },
              {
                "label": "Carteggio.1850.2a ",
                "target": "b277bf",
                "chapter": "04"
              },
              {
                "label": "Carteggio.1850.2b ",
                "target": "67d677",
                "chapter": "04"
              },
              {
                "label": "Carteggio.1852.1 ",
                "target": "81447f",
                "chapter": "04"
              },
              {
                "label": "Carteggio.1852.2 ",
                "target": "ed9b0c",
                "chapter": "04"
              },
              {
                "label": "Carteggio.1852.3 ",
                "target": "edcdbe",
                "chapter": "04"
              },
              {
                "label": "Carteggio.1852.4 ",
                "target": "f695b4",
                "chapter": "04"
              },
              {
                "label": "Carteggio.1852.5 ",
                "target": "e12ff0",
                "chapter": "04"
              },
              {
                "label": "Carteggio.1852.6 ",
                "target": "55d23b",
                "chapter": "04"
              },
              {
                "label": "Carteggio.1853.1 ",
                "target": "f0e0da",
                "chapter": "04"
              },
              {
                "label": "Carteggio.1853.2 ",
                "target": "08286d",
                "chapter": "04"
              },
              {
                "label": "Carteggio.1853.3 ",
                "target": "7b496f",
                "chapter": "04"
              },
              {
                "label": "Carteggio.1853.4 ",
                "target": "fe0b59",
                "chapter": "04"
              },
              {
                "label": "Carteggio.1853.5 ",
                "target": "e91f32",
                "chapter": "04"
              },
              {
                "label": "Carteggio.1854.1 ",
                "target": "2982f8",
                "chapter": "04"
              },
              {
                "label": "Carteggio.1854.2 ",
                "target": "9a75f7",
                "chapter": "04"
              },
              {
                "label": "Carteggio.1855.1 ",
                "target": "b725e5",
                "chapter": "04"
              },
              {
                "label": "Carteggio.1855.2 ",
                "target": "9fdbe0",
                "chapter": "04"
              },
              {
                "label": "Carteggio.1855.3 ",
                "target": "a06bef",
                "chapter": "04"
              },
              {
                "label": "Carteggio.1855.4 ",
                "target": "27d59d",
                "chapter": "04"
              },
              {
                "label": "Carteggio.1858.1 ",
                "target": "bf302c",
                "chapter": "04"
              },
              {
                "label": "Carteggio.1863.1 ",
                "target": "238fe7",
                "chapter": "04"
              }
            ]
          },
          {
            "name": "5. Depositi",
            "subtitle": "Elenco dei prodotti depositati ufficialmente presso il Consiglio di\n                  Stato ticinese\n            ",
            "group": [
              {
                "name": "5. Depositi - Carlo Pozzi (1836–1855)",
                "target": "c8737b",
                "link": [
                  {
                    "label": "a) sintesi cronologica",
                    "target": "1b8d8f",
                    "chapter": "05"
                  },
                  {
                    "label": "b) sintesi quantitativa e per tipologie",
                    "target": "408268",
                    "chapter": "05"
                  },
                  {
                    "label": "> sintesi quantitativa dei materiali documentati (forma\n                  riassuntiva)",
                    "target": "09dbf6",
                    "chapter": "05"
                  },
                  {
                    "label": "> sintesi quantitativa dei materiali documentati (forma\n                  completa)",
                    "target": "69f748",
                    "chapter": "05"
                  },
                  {
                    "label": "> sintesi dei materiali documentati per tipologie (forma\n                  ridotta)",
                    "target": "a31bf2",
                    "chapter": "05"
                  }
                ]
              },
              {
                "name": "5. Depositi - Gioachino Spinelli / Euterpe Ticinese (1838–1854)",
                "target": "156420",
                "link": [
                  {
                    "label": "a) sintesi cronologica",
                    "target": "6c5f8b",
                    "chapter": "05"
                  },
                  {
                    "label": "b) sintesi quantitativa e per tipologie",
                    "target": "3a1003",
                    "chapter": "05"
                  },
                  {
                    "label": "> sintesi quantitativa dei materiali documentati (forma ridotta)",
                    "target": "3d481f",
                    "chapter": "05"
                  },
                  {
                    "label": "> sintesi quantitativa dei materiali documentati (forma\n                  completa)",
                    "target": "94569c",
                    "chapter": "05"
                  },
                  {
                    "label": "> sintesi dei materiali documentati per tipologie",
                    "target": "aaef38",
                    "chapter": "05"
                  }
                ]
              },
              {
                "name": "5. Depositi - Achille Bustelli-Rossi (1857–1867)",
                "target": "4b5b1c",
                "link": [
                  {
                    "label": "a) sintesi cronologica",
                    "target": "5fe321",
                    "chapter": "05"
                  },
                  {
                    "label": "b) sintesi quantitativa e per tipologie",
                    "target": "d72eb6",
                    "chapter": "05"
                  },
                  {
                    "label": "> sintesi quantitativa dei materiali documentati (forma\n                  riassuntiva)",
                    "target": "f0f51a",
                    "chapter": "05"
                  },
                  {
                    "label": "> sintesi quantitativa dei materiali documentati (forma\n                  completa)",
                    "target": "1d5f84",
                    "chapter": "05"
                  },
                  {
                    "label": "> sintesi dei materiali documentati per tipologie",
                    "target": "f25749",
                    "chapter": "05"
                  }
                ]
              },
              {
                "name": "5. Depositi - Francesco Veladini (1860–1866)",
                "target": "b9e280",
                "link": [
                  {
                    "label": "> sintesi cronologica",
                    "target": "5b3392",
                    "chapter": "05"
                  }
                ]
              }
            ]
          },
          {
            "name": "6. Cataloghi",
            "subtitle": "Elenco dei prodotti realizzati dai protagonisti dell’editoria\n                  musicale ticinese, non\n                  depositati ",
            "group": [
              {
                "name": "6. Cataloghi - Catalogo delle musiche prodotte da Carlo Pozzi",
                "target": "b1af37",
                "link": [
                  {
                    "label": "a) in ordine numerico",
                    "target": "a17fa3",
                    "chapter": "06"
                  },
                  {
                    "label": "> elenco numerico",
                    "target": "1a97bb",
                    "chapter": "06"
                  },
                  {
                    "label": "b) in ordine tematico",
                    "target": "1a7638",
                    "chapter": "06"
                  }
                ]
              },
              {
                "name": "6. Cataloghi - Catalogo delle musiche prodotte da Euterpe Ticinese",
                "target": "d432e1",
                "link": [
                  {
                    "label": "a) in ordine numerico",
                    "target": "648e91",
                    "chapter": "06"
                  },
                  {
                    "label": "> elenco numerico",
                    "target": "83bc86",
                    "chapter": "06"
                  },
                  {
                    "label": "b) in ordine tematico",
                    "target": "511a9d",
                    "chapter": "06"
                  }
                ]
              },
              {
                "name": "6. Cataloghi - Catalogo delle musiche prodotte da Achille Bustelli-Rossi",
                "target": "fd94f6",
                "link": [
                  {
                    "label": "a) in ordine numerico",
                    "target": "121a5b",
                    "chapter": "06"
                  },
                  {
                    "label": "> elenco numerico",
                    "target": "3f3971",
                    "chapter": "06"
                  },
                  {
                    "label": "b) in ordine tematico",
                    "target": "a66e25",
                    "chapter": "06"
                  }
                ]
              }
            ]
          },
          {
            "name": "7. Petizioni",
            "subtitle": "Raccolta delle petizioni presentate al Consiglio di Stato ticinese\n                  per ottenere il\n                  beneficio giusta la legge 20 maggio 1835 sulla protezione della proprietà letteraria (in ordine\n                  cronologico) ",
            "link": [
              {
                "label": "7. Petizioni - Pozzi (1839–1855)",
                "target": "f1678e",
                "chapter": "07"
              },
              {
                "label": "7. Petizioni - Spinelli / Euterpe Ticinese (1840–1854)",
                "target": "862e17",
                "chapter": "07"
              },
              {
                "label": "7. Petizioni - Bustelli-Rossi (1859–1867)",
                "target": "d11b73",
                "chapter": "07"
              }
            ]
          },
          {
            "name": "8. Avvisi musicali",
            "subtitle": "Raccolta degli annunci lanciati dagli editori musicali ticinesi sui\n                  principali organi\n                  ufficiali e di stampa per diffidare la ristampa dei prodotti depositati (in ordine cronologico)\n      ",
            "link": [
              {
                "label": "8. Avvisi musicali pubblicati da Carlo Pozzi",
                "target": "00e11a",
                "chapter": "08"
              },
              {
                "label": "8. Avvisi musicali pubblicati da Gioachino Spinelli (Euterpe Ticinese)",
                "target": "6d7cf2",
                "chapter": "08"
              },
              {
                "label": "8. Avvisi musicali pubblicati da Achille Bustelli-Rossi",
                "target": "469f39",
                "chapter": "08"
              }
            ]
          },
          {
            "name": "9. Documenti vari",
            "subtitle": "Avvisi pubblici, testi di legge, documenti governativi (1815–1900):\n                  materiali non compresi nelle precedenti rubriche (in ordine cronologico) ",
            "link": [
              {
                "label": "Documenti.vari.1815.1",
                "target": "e8dbdc",
                "chapter": "09"
              },
              {
                "label": "Documenti.vari.1816.1",
                "target": "ae1ae8",
                "chapter": "09"
              },
              {
                "label": "Documenti.vari.1831.1",
                "target": "bdfd9f",
                "chapter": "09"
              },
              {
                "label": "Documenti.vari.1831.2",
                "target": "7da88a",
                "chapter": "09"
              },
              {
                "label": "Documenti.vari.1831.3",
                "target": "e6af16",
                "chapter": "09"
              },
              {
                "label": "Documenti.vari.1831.4",
                "target": "d45265",
                "chapter": "09"
              },
              {
                "label": "Documenti.vari.1833.1",
                "target": "c479d9",
                "chapter": "09"
              },
              {
                "label": "Documenti.vari.1835.1",
                "target": "9f9b21",
                "chapter": "09"
              },
              {
                "label": "Documenti.vari.1840.1",
                "target": "daf6a7",
                "chapter": "09"
              },
              {
                "label": "Documenti.vari.1841.1",
                "target": "f17484",
                "chapter": "09"
              },
              {
                "label": "Documenti.vari.1842.1",
                "target": "8a8ae2",
                "chapter": "09"
              },
              {
                "label": "Documenti.vari.1850.1",
                "target": "b00ad4",
                "chapter": "09"
              },
              {
                "label": "Documenti.vari.1850.2",
                "target": "43998c",
                "chapter": "09"
              },
              {
                "label": "Documenti.vari.1853.1",
                "target": "01b274",
                "chapter": "09"
              },
              {
                "label": "Documenti.vari.1858.1",
                "target": "ec5082",
                "chapter": "09"
              },
              {
                "label": "Documenti.vari.1863.1",
                "target": "1b655e",
                "chapter": "09"
              },
              {
                "label": "Documenti.vari.1868.1",
                "target": "f42331",
                "chapter": "09"
              },
              {
                "label": "Documenti.vari.1869.1",
                "target": "d6e9e9",
                "chapter": "09"
              },
              {
                "label": "Documenti.vari.1869.2",
                "target": "fd7825",
                "chapter": "09"
              },
              {
                "label": "Documenti.vari.1870.1",
                "target": "339b64",
                "chapter": "09"
              },
              {
                "label": "Documenti.vari.1870.2",
                "target": "0d059b",
                "chapter": "09"
              },
              {
                "label": "Documenti.vari.1883.1",
                "target": "e086bc",
                "chapter": "09"
              },
              {
                "label": "Documenti.vari.1886.1",
                "target": "4a0699",
                "chapter": "09"
              },
              {
                "label": "Documenti.vari.1900.1",
                "target": "6caed8",
                "chapter": "09"
              }
            ]
          },
          {
            "name": "10. Illustrazioni",
            "link": [
              {
                "label": "Illustrazione 1",
                "target": "7652b1",
                "chapter": "10"
              },
              {
                "label": "Illustrazione 2",
                "target": "fb88f5",
                "chapter": "10"
              },
              {
                "label": "Illustrazione 3",
                "target": "5b7485",
                "chapter": "10"
              },
              {
                "label": "Illustrazione 4a",
                "target": "f50df9",
                "chapter": "10"
              },
              {
                "label": "Illustrazione 4b",
                "target": "22589e",
                "chapter": "10"
              },
              {
                "label": "Illustrazione 5a",
                "target": "9ab7c9",
                "chapter": "10"
              },
              {
                "label": "Illustrazione 5b",
                "target": "ec710b",
                "chapter": "10"
              },
              {
                "label": "Illustrazione 6a-b",
                "target": "0b9c27",
                "chapter": "10"
              },
              {
                "label": "Illustrazione 6c-d",
                "target": "3b088f",
                "chapter": "10"
              },
              {
                "label": "Illustrazione 7a",
                "target": "c0570f",
                "chapter": "10"
              },
              {
                "label": "Illustrazione 7b",
                "target": "f8a8fd",
                "chapter": "10"
              },
              {
                "label": "Illustrazione 8a",
                "target": "d405eb",
                "chapter": "10"
              },
              {
                "label": "Illustrazione 8b",
                "target": "f8133b",
                "chapter": "10"
              },
              {
                "label": "Illustrazione 8c-d",
                "target": "89e878",
                "chapter": "10"
              },
              {
                "label": "Illustrazione 9",
                "target": "416337",
                "chapter": "10"
              },
              {
                "label": "Illustrazione 10a-b",
                "target": "68b779",
                "chapter": "10"
              },
              {
                "label": "Illustrazione 11a-b",
                "target": "167746",
                "chapter": "10"
              },
              {
                "label": "Illustrazione 12a-c",
                "target": "28d888",
                "chapter": "10"
              },
              {
                "label": "Illustrazione 13",
                "target": "881303",
                "chapter": "10"
              },
              {
                "label": "Illustrazione 14",
                "target": "30d8cd",
                "chapter": "10"
              },
              {
                "label": "Illustrazione 15a-b",
                "target": "ab464c",
                "chapter": "10"
              },
              {
                "label": "Illustrazione 16",
                "target": "1749b2",
                "chapter": "10"
              },
              {
                "label": "Illustrazione 17a-b",
                "target": "26fc80",
                "chapter": "10"
              },
              {
                "label": "Illustrazione 18a-b",
                "target": "61e6f3",
                "chapter": "10"
              },
              {
                "label": "Illustrazione 18c",
                "target": "50cdaa",
                "chapter": "10"
              },
              {
                "label": "Illustrazione 19a-b",
                "target": "609a5d",
                "chapter": "10"
              },
              {
                "label": "Illustrazione 19c-d",
                "target": "1c6996",
                "chapter": "10"
              },
              {
                "label": "Illustrazione 19e",
                "target": "d32177",
                "chapter": "10"
              },
              {
                "label": "Illustrazione 20a-c",
                "target": "67da52",
                "chapter": "10"
              },
              {
                "label": "Illustrazione 21",
                "target": "ba4eb8",
                "chapter": "10"
              },
              {
                "label": "Illustrazione 22",
                "target": "c9b617",
                "chapter": "10"
              },
              {
                "label": "Illustrazione 23",
                "target": "c3bf9e",
                "chapter": "10"
              },
              {
                "label": "Illustrazione 24",
                "target": "95eff7",
                "chapter": "10"
              },
              {
                "label": "Illustrazione 25a-c",
                "target": "708d0d",
                "chapter": "10"
              },
              {
                "label": "Illustrazione 25d-e",
                "target": "70a3ad",
                "chapter": "10"
              },
              {
                "label": "Illustrazione 26a",
                "target": "db45ec",
                "chapter": "10"
              },
              {
                "label": "Illustrazione 26b",
                "target": "0acef3",
                "chapter": "10"
              },
              {
                "label": "Illustrazione 26c",
                "target": "f2d8d1",
                "chapter": "10"
              },
              {
                "label": "Illustrazione 24",
                "target": "44c941",
                "chapter": "10"
              },
              {
                "label": "Illustrazione 26d",
                "target": "bb957d",
                "chapter": "10"
              },
              {
                "label": "Illustrazione 27",
                "target": "1787e8",
                "chapter": "10"
              },
              {
                "label": "Illustrazione 28a-b",
                "target": "ba9209",
                "chapter": "10"
              },
              {
                "label": "Illustrazione 29a-b",
                "target": "74bf6d",
                "chapter": "10"
              },
              {
                "label": "Illustrazione 30a-b",
                "target": "9c32c9",
                "chapter": "10"
              },
              {
                "label": "Illustrazione 31",
                "target": "f916cb",
                "chapter": "10"
              },
              {
                "label": "Illustrazione 32",
                "target": "47d6dc",
                "chapter": "10"
              },
              {
                "label": "Illustrazione 33",
                "target": "9dd419",
                "chapter": "10"
              },
              {
                "label": "Illustrazione 34",
                "target": "416e89",
                "chapter": "10"
              },
              {
                "label": "Illustrazione 35",
                "target": "3d8540",
                "chapter": "10"
              },
              {
                "label": "Illustrazione 36a-c",
                "target": "6bdf6d",
                "chapter": "10"
              },
              {
                "label": "Illustrazione 37a-b",
                "target": "cfb240",
                "chapter": "10"
              }
            ]
          },
          {
            "name": "11. Abbreviazioni  -  Bibliografia",
            "link": [
              {
                "label": "Archivi e biblioteche",
                "target": "433248",
                "chapter": "11"
              },
              {
                "label": "Fonti ufficiali a stampa",
                "target": "d4098d",
                "chapter": "11"
              },
              {
                "label": "Altre sigle",
                "target": "717ef0",
                "chapter": "11"
              },
              {
                "label": "Riferimenti bibliografici",
                "target": "160583",
                "chapter": "11"
              }
            ]
          }
        ]
      }
    ]
  }
}