[
  {
    "id": "2c6c9a",
    "string": "1. Introduzione"
  },
  {
    "id": "56c217",
    "string": "1 settembre 1833"
  },
  {
    "id": "6e455c",
    "string": "1 gennaio 1884"
  },
  {
    "id": "d780d4",
    "string": "1 settembre 1842"
  },
  {
    "id": "f1bf3e",
    "string": "1 settembre 1845"
  },
  {
    "id": "1bce42",
    "string": "1 marzo 1849"
  },
  {
    "id": "c1de6f",
    "string": "1 febbraio 1850"
  },
  {
    "id": "590525",
    "string": "1 luglio 1845"
  },
  {
    "id": "a62071",
    "string": "1 marzo 1849"
  },
  {
    "id": "ba11d2",
    "string": "1 settembre 1852"
  },
  {
    "id": "7c54de",
    "string": "2. Studio generale"
  },
  {
    "id": "33b354",
    "string": "2 ottobre 1842"
  },
  {
    "id": "777449",
    "string": "2 novembre 1842"
  },
  {
    "id": "b4600a",
    "string": "2 dicembre 1844"
  },
  {
    "id": "f224be",
    "string": "2 giugno 1846"
  },
  {
    "id": "c6c19d",
    "string": "2 marzo 1850"
  },
  {
    "id": "bd9592",
    "string": "2 aprile 1851"
  },
  {
    "id": "f5a3d8",
    "string": "2 novembre 1846"
  },
  {
    "id": "0793e3",
    "string": "2 novembre 1847"
  },
  {
    "id": "61a896",
    "string": "2 febbraio 1853"
  },
  {
    "id": "7a1de5",
    "string": "3. Cronologia"
  },
  {
    "id": "289c16",
    "string": "3 dicembre 1833"
  },
  {
    "id": "ab7daf",
    "string": "3 luglio 1836"
  },
  {
    "id": "cc6ef0",
    "string": "3 luglio 1842"
  },
  {
    "id": "9fc5f3",
    "string": "3 aprile 1843"
  },
  {
    "id": "76a27a",
    "string": "3 giugno 1851"
  },
  {
    "id": "247f06",
    "string": "3 febbraio 1850"
  },
  {
    "id": "e4f2aa",
    "string": "3 febbraio 1852"
  },
  {
    "id": "96bce0",
    "string": "4 agosto 1815"
  },
  {
    "id": "6a7a3f",
    "string": "4 giugno 1816"
  },
  {
    "id": "296655",
    "string": "4 giugno 1836"
  },
  {
    "id": "42834b",
    "string": "4. Carteggio"
  },
  {
    "id": "9cde24",
    "string": "4 novembre 1844"
  },
  {
    "id": "bde27d",
    "string": "4 agosto 1850"
  },
  {
    "id": "d4a254",
    "string": "4 gennaio 1853"
  },
  {
    "id": "077efd",
    "string": "5. Depositi"
  },
  {
    "id": "87e497",
    "string": "5. Depositi - Carlo Pozzi (1836–1855)"
  },
  {
    "id": "abb7c7",
    "string": "5 agosto 1842"
  },
  {
    "id": "49901b",
    "string": "5 aprile 1845"
  },
  {
    "id": "c62891",
    "string": "5. Depositi - Carlo Pozzi (1836–1855)"
  },
  {
    "id": "1372af",
    "string": "5. Depositi - Carlo Pozzi (1836–1855)"
  },
  {
    "id": "a499c2",
    "string": "5. Depositi - Carlo Pozzi (1836–1855)"
  },
  {
    "id": "3d318f",
    "string": "5. Depositi - Carlo Pozzi (1836–1855)"
  },
  {
    "id": "0d1624",
    "string": "5. Depositi - Gioachino Spinelli / Euterpe Ticinese (1838–1854)"
  },
  {
    "id": "953d9b",
    "string": "5 aprile 1846"
  },
  {
    "id": "e14c3e",
    "string": "5 maggio 1851"
  },
  {
    "id": "0c5f39",
    "string": "5 giugno 1851"
  },
  {
    "id": "06e651",
    "string": "5. Depositi - Gioachino Spinelli / Euterpe Ticinese (1838–1854)"
  },
  {
    "id": "f6a3fa",
    "string": "5. Depositi - Gioachino Spinelli / Euterpe Ticinese (1838–1854)"
  },
  {
    "id": "f77a62",
    "string": "5. Depositi - Gioachino Spinelli / Euterpe Ticinese (1838–1854)"
  },
  {
    "id": "4df577",
    "string": "5. Depositi - Gioachino Spinelli / Euterpe Ticinese (1838–1854)"
  },
  {
    "id": "ec69e6",
    "string": "5. Depositi - Achille Bustelli-Rossi (1857–1867)"
  },
  {
    "id": "997cc7",
    "string": "5 luglio 1862"
  },
  {
    "id": "bfd333",
    "string": "5. Depositi - Achille Bustelli-Rossi (1857–1867)"
  },
  {
    "id": "2b31be",
    "string": "5. Depositi - Achille Bustelli-Rossi (1857–1867)"
  },
  {
    "id": "e1bfc8",
    "string": "5. Depositi - Achille Bustelli-Rossi (1857–1867)"
  },
  {
    "id": "b506e7",
    "string": "5. Depositi - Achille Bustelli-Rossi (1857–1867)"
  },
  {
    "id": "fe3878",
    "string": "5. Depositi - Francesco Veladini (1860–1866)"
  },
  {
    "id": "fe763c",
    "string": "6 febbraio 1843"
  },
  {
    "id": "d92190",
    "string": "6 aprile 1843"
  },
  {
    "id": "7045ae",
    "string": "6 luglio 1843"
  },
  {
    "id": "0e5e44",
    "string": "6 ottobre 1849"
  },
  {
    "id": "443dee",
    "string": "6 gennaio 1850"
  },
  {
    "id": "8c5e27",
    "string": "6 dicembre 1849"
  },
  {
    "id": "615fee",
    "string": "6 marzo 1851"
  },
  {
    "id": "24fd4d",
    "string": "6 luglio 1851"
  },
  {
    "id": "40f94a",
    "string": "6 ottobre 1851"
  },
  {
    "id": "f975f7",
    "string": "6 dicembre 1862"
  },
  {
    "id": "f92c85",
    "string": "6. Cataloghi"
  },
  {
    "id": "08fefc",
    "string": "6. Cataloghi - Catalogo delle musiche prodotte da Carlo Pozzi"
  },
  {
    "id": "56e003",
    "string": "6. Cataloghi - Catalogo delle musiche prodotte da Euterpe Ticinese"
  },
  {
    "id": "b1a814",
    "string": "6. Cataloghi - Catalogo delle musiche prodotte da Achille Bustelli-Rossi"
  },
  {
    "id": "4c5e21",
    "string": "7 agosto 1842"
  },
  {
    "id": "efcd76",
    "string": "7 marzo 1843"
  },
  {
    "id": "48dbdc",
    "string": "7 dicembre 1844"
  },
  {
    "id": "348e88",
    "string": "7 giugno 1848"
  },
  {
    "id": "6eebcc",
    "string": "7 marzo 1850"
  },
  {
    "id": "9c25a5",
    "string": "7. Petizioni"
  },
  {
    "id": "781d86",
    "string": "7. Petizioni - Pozzi (1839–1855)"
  },
  {
    "id": "763f4a",
    "string": "7. Petizioni - Spinelli / Euterpe Ticinese (1840–1854)"
  },
  {
    "id": "68efbd",
    "string": "7. Petizioni - Bustelli-Rossi (1859–1867)"
  },
  {
    "id": "401c37",
    "string": "8 aprile 1845"
  },
  {
    "id": "431648",
    "string": "8 ottobre 1845"
  },
  {
    "id": "ce7bf0",
    "string": "8 dicembre 1845"
  },
  {
    "id": "7c552e",
    "string": "8 aprile 1847"
  },
  {
    "id": "6c95f9",
    "string": "8 gennaio 1851"
  },
  {
    "id": "f2e2f6",
    "string": "8 agosto 1847"
  },
  {
    "id": "8bfa05",
    "string": "8. Avvisi musicali"
  },
  {
    "id": "bbf017",
    "string": "8. Avvisi musicali pubblicati da Carlo Pozzi"
  },
  {
    "id": "5181f5",
    "string": "8. Avvisi musicali pubblicati da Gioachino Spinelli (Euterpe Ticinese)"
  },
  {
    "id": "5287bc",
    "string": "8. Avvisi musicali pubblicati da Achille Bustelli-Rossi"
  },
  {
    "id": "dce5e6",
    "string": "9 gennaio 1835"
  },
  {
    "id": "ab9a37",
    "string": "9 febbraio 1842"
  },
  {
    "id": "b5ee1e",
    "string": "9 settembre 1842"
  },
  {
    "id": "5c223f",
    "string": "9 febbraio 1843"
  },
  {
    "id": "3fa61f",
    "string": "9 dicembre 1843"
  },
  {
    "id": "9b61c2",
    "string": "9 agosto 1855"
  },
  {
    "id": "1537bc",
    "string": "9 giugno 1846"
  },
  {
    "id": "d927f0",
    "string": "9 dicembre 1851"
  },
  {
    "id": "5cb004",
    "string": "9 maggio 1852"
  },
  {
    "id": "f64922",
    "string": "9. Documenti vari"
  },
  {
    "id": "7eb387",
    "string": "10 febbraio 1845"
  },
  {
    "id": "1139cf",
    "string": "10 luglio 1867"
  },
  {
    "id": "555cc7",
    "string": "10 aprile 1851"
  },
  {
    "id": "9f5e1f",
    "string": "10 luglio 1867"
  },
  {
    "id": "e9b0b6",
    "string": "10. Illustrazioni"
  },
  {
    "id": "654623",
    "string": "11 ottobre 1843"
  },
  {
    "id": "135376",
    "string": "11 agosto 1851"
  },
  {
    "id": "f9ce82",
    "string": "11 giugno 1852"
  },
  {
    "id": "4306e8",
    "string": "11. Abbreviazioni  -  Bibliografia"
  },
  {
    "id": "8ce26d",
    "string": "12 maggio 1843"
  },
  {
    "id": "314dff",
    "string": "12 gennaio 1847"
  },
  {
    "id": "489175",
    "string": "12 maggio 1853"
  },
  {
    "id": "f6277b",
    "string": "13 maggio 1869"
  },
  {
    "id": "e02190",
    "string": "13 dicembre 1842"
  },
  {
    "id": "851836",
    "string": "13 febbraio 1847"
  },
  {
    "id": "32238b",
    "string": "13 settembre 1849"
  },
  {
    "id": "a0a164",
    "string": "13 agosto 1853"
  },
  {
    "id": "053ebd",
    "string": "13 aprile 1846"
  },
  {
    "id": "bcbb53",
    "string": "13 ottobre 1850"
  },
  {
    "id": "11622c",
    "string": "13 novembre 1853"
  },
  {
    "id": "44f6f1",
    "string": "14 dicembre 1858"
  },
  {
    "id": "d941cc",
    "string": "14 giugno 1843"
  },
  {
    "id": "4ef514",
    "string": "14 agosto 1843"
  },
  {
    "id": "3b6cd4",
    "string": "14 novembre 1844"
  },
  {
    "id": "126b54",
    "string": "14 ottobre 1845"
  },
  {
    "id": "ffa875",
    "string": "14 agosto 1845"
  },
  {
    "id": "70e22e",
    "string": "14 febbraio 1846"
  },
  {
    "id": "2fdb88",
    "string": "14 aprile 1851"
  },
  {
    "id": "0a4e36",
    "string": "14 marzo 1867"
  },
  {
    "id": "ba18d6",
    "string": "15 aprile 1837"
  },
  {
    "id": "df82fd",
    "string": "15 maggio 1841"
  },
  {
    "id": "70fa2a",
    "string": "15 novembre 1850"
  },
  {
    "id": "988e23",
    "string": "15 marzo 1853"
  },
  {
    "id": "5759ab",
    "string": "15 dicembre 1858"
  },
  {
    "id": "5b9d6b",
    "string": "15 ottobre 1842"
  },
  {
    "id": "f2da66",
    "string": "15 gennaio 1843"
  },
  {
    "id": "cc49d6",
    "string": "15 marzo 1850"
  },
  {
    "id": "4391b0",
    "string": "15 ottobre 1846"
  },
  {
    "id": "d9dae6",
    "string": "15 settembre 1851"
  },
  {
    "id": "13d6ad",
    "string": "16 dicembre 1839"
  },
  {
    "id": "517738",
    "string": "16 agosto 1842"
  },
  {
    "id": "2cf930",
    "string": "16 settembre 1842"
  },
  {
    "id": "7e51cc",
    "string": "16 novembre 1844"
  },
  {
    "id": "317e81",
    "string": "16 aprile 1845"
  },
  {
    "id": "7d00f0",
    "string": "16 giugno 1848"
  },
  {
    "id": "0e5ccb",
    "string": "16 ottobre 1847"
  },
  {
    "id": "15df72",
    "string": "16 settembre 1850"
  },
  {
    "id": "adc5c9",
    "string": "16 dicembre 1850"
  },
  {
    "id": "25ba90",
    "string": "16 gennaio 1853"
  },
  {
    "id": "a469c8",
    "string": "17 gennaio 1840"
  },
  {
    "id": "df7679",
    "string": "17 gennaio 1853"
  },
  {
    "id": "5df7db",
    "string": "17 marzo 1861"
  },
  {
    "id": "646dac",
    "string": "17 agosto 1868"
  },
  {
    "id": "e484d6",
    "string": "17 settembre 1849"
  },
  {
    "id": "067c59",
    "string": "17 maggio 1851"
  },
  {
    "id": "cdb2c4",
    "string": "17 febbraio 1853"
  },
  {
    "id": "26dec1",
    "string": "17 marzo 1853"
  },
  {
    "id": "eeb906",
    "string": "17 gennaio 1840"
  },
  {
    "id": "79198e",
    "string": "17 dicembre 1845"
  },
  {
    "id": "13eedf",
    "string": "17 gennaio 1850"
  },
  {
    "id": "1449cd",
    "string": "17 novembre 1850"
  },
  {
    "id": "db5474",
    "string": "18 febbraio 1847"
  },
  {
    "id": "5aa9da",
    "string": "18 ottobre 1850"
  },
  {
    "id": "d5515d",
    "string": "18 luglio 1842"
  },
  {
    "id": "bbe01d",
    "string": "18 settembre 1843"
  },
  {
    "id": "2ae0f5",
    "string": "18 giugno 1844"
  },
  {
    "id": "4ac544",
    "string": "18 marzo 1848"
  },
  {
    "id": "578fe3",
    "string": "19 ottobre 1855"
  },
  {
    "id": "f53cb7",
    "string": "19 maggio 1902"
  },
  {
    "id": "c79350",
    "string": "19 gennaio 1840"
  },
  {
    "id": "c4c5ad",
    "string": "19 gennaio 1846"
  },
  {
    "id": "d1db0b",
    "string": "19 febbraio 1854"
  },
  {
    "id": "29e4f7",
    "string": "20 ottobre 1833"
  },
  {
    "id": "92c1c3",
    "string": "20 maggio 1835"
  },
  {
    "id": "9be60f",
    "string": "20 settembre 1869"
  },
  {
    "id": "549fba",
    "string": "20 novembre 1872"
  },
  {
    "id": "436bb3",
    "string": "20 marzo 1842"
  },
  {
    "id": "774fdc",
    "string": "20 dicembre 1842"
  },
  {
    "id": "4401dd",
    "string": "20 ottobre 1849"
  },
  {
    "id": "84fb78",
    "string": "20 novembre 1850"
  },
  {
    "id": "8b70ee",
    "string": "20 luglio 1845"
  },
  {
    "id": "d5e982",
    "string": "20 giugno 1853"
  },
  {
    "id": "87220b",
    "string": "20 aprile 1854"
  },
  {
    "id": "3a0add",
    "string": "21 aprile 1870"
  },
  {
    "id": "be3078",
    "string": "21 febbraio 1842"
  },
  {
    "id": "623e2a",
    "string": "21 ottobre 1842"
  },
  {
    "id": "3b63da",
    "string": "21 aprile 1847"
  },
  {
    "id": "32655e",
    "string": "21 maggio 1851"
  },
  {
    "id": "0ca3d7",
    "string": "21 agosto 1855"
  },
  {
    "id": "0a0706",
    "string": "21 febbraio 1847"
  },
  {
    "id": "ca6fbd",
    "string": "22 maggio 1840"
  },
  {
    "id": "feb3a6",
    "string": "22 settembre 1840"
  },
  {
    "id": "57b862",
    "string": "22 luglio 1868"
  },
  {
    "id": "6531a7",
    "string": "22 luglio 1843"
  },
  {
    "id": "84f357",
    "string": "22 dicembre 1849"
  },
  {
    "id": "73e934",
    "string": "22 maggio 1851"
  },
  {
    "id": "93258e",
    "string": "23 settembre 1837"
  },
  {
    "id": "780bf6",
    "string": "23 marzo 1847"
  },
  {
    "id": "b90348",
    "string": "23 aprile 1850"
  },
  {
    "id": "ddfd38",
    "string": "23 aprile 1853"
  },
  {
    "id": "68f9a0",
    "string": "23 aprile 1846"
  },
  {
    "id": "da4e1a",
    "string": "23 dicembre 1849"
  },
  {
    "id": "11a13c",
    "string": "23 dicembre 1850"
  },
  {
    "id": "b10c37",
    "string": "23 aprile 1867"
  },
  {
    "id": "7e7327",
    "string": "24 luglio 1850"
  },
  {
    "id": "d1efde",
    "string": "24 agosto 1842"
  },
  {
    "id": "372245",
    "string": "24 settembre 1842"
  },
  {
    "id": "fd45c5",
    "string": "24 gennaio 1843"
  },
  {
    "id": "221bbf",
    "string": "24 settembre 1845"
  },
  {
    "id": "798329",
    "string": "24 gennaio 1851"
  },
  {
    "id": "ab79ec",
    "string": "24 aprile 1851"
  },
  {
    "id": "f5c325",
    "string": "24 febbraio 1850"
  },
  {
    "id": "c7163a",
    "string": "25 giugno 1846"
  },
  {
    "id": "fabf73",
    "string": "25 luglio 1850"
  },
  {
    "id": "bc58ab",
    "string": "26 marzo 1852"
  },
  {
    "id": "dcda40",
    "string": "26 febbraio 1855"
  },
  {
    "id": "381c7a",
    "string": "26 dicembre 1841"
  },
  {
    "id": "502572",
    "string": "26 gennaio 1842"
  },
  {
    "id": "546b31",
    "string": "26 febbraio 1842"
  },
  {
    "id": "7811ed",
    "string": "26 ottobre 1846"
  },
  {
    "id": "972d98",
    "string": "26 febbraio 1859"
  },
  {
    "id": "87d28b",
    "string": "27 marzo 1855"
  },
  {
    "id": "2bb2b5",
    "string": "27 marzo 1843"
  },
  {
    "id": "1369d6",
    "string": "27 novembre 1845"
  },
  {
    "id": "86f9b6",
    "string": "27 settembre 1847"
  },
  {
    "id": "7965ff",
    "string": "27 ottobre 1851"
  },
  {
    "id": "6c8334",
    "string": "27 dicembre 1851"
  },
  {
    "id": "fbed39",
    "string": "28 maggio 1838"
  },
  {
    "id": "e99dc5",
    "string": "28 dicembre 1852"
  },
  {
    "id": "254596",
    "string": "28 maggio 1854"
  },
  {
    "id": "97db2e",
    "string": "28 gennaio 1849"
  },
  {
    "id": "b210ee",
    "string": "28 aprile 1851"
  },
  {
    "id": "68aa4f",
    "string": "28 maggio 1854"
  },
  {
    "id": "148088",
    "string": "29 agosto 1844"
  },
  {
    "id": "a7e55b",
    "string": "29 marzo 1845"
  },
  {
    "id": "4fbdd4",
    "string": "29 novembre 1846"
  },
  {
    "id": "0ff7ef",
    "string": "29 luglio 1847"
  },
  {
    "id": "92af7c",
    "string": "30 maggio 1888"
  },
  {
    "id": "680125",
    "string": "30 marzo 1842"
  },
  {
    "id": "e9aa02",
    "string": "30 giugno 1843"
  },
  {
    "id": "611cde",
    "string": "30 giugno 1845"
  },
  {
    "id": "579db1",
    "string": "30 marzo 1850"
  },
  {
    "id": "c65c27",
    "string": "30 giugno 1862"
  },
  {
    "id": "732e0f",
    "string": "31 dicembre 1844"
  },
  {
    "id": "9e6b1e",
    "string": "31 gennaio 1853"
  },
  {
    "id": "b4a01d",
    "string": "31 marzo 1853"
  },
  {
    "id": "2b39d0",
    "string": "31 maggio 1846"
  },
  {
    "id": "c3f9d5",
    "string": "31 marzo 1851"
  },
  {
    "id": "502e4d",
    "string": "31 agosto 1851"
  },
  {
    "id": "b0bec9",
    "string": "1808"
  },
  {
    "id": "a7f2e9",
    "string": "1814–1815"
  },
  {
    "id": "306189",
    "string": "1816"
  },
  {
    "id": "e8154c",
    "string": "1825"
  },
  {
    "id": "d81b44",
    "string": "1826"
  },
  {
    "id": "cf4ae6",
    "string": "1828"
  },
  {
    "id": "8812dd",
    "string": "1830"
  },
  {
    "id": "17ac10",
    "string": "1838"
  },
  {
    "id": "78dc7f",
    "string": "1842"
  },
  {
    "id": "092c53",
    "string": "1844"
  },
  {
    "id": "0e7289",
    "string": "1848"
  },
  {
    "id": "47dd48",
    "string": "1851–1855"
  },
  {
    "id": "6d5a52",
    "string": "1857"
  },
  {
    "id": "2173c5",
    "string": "1860–1868"
  },
  {
    "id": "28ffe5",
    "string": "1886"
  },
  {
    "id": "3446fb",
    "string": "1887"
  },
  {
    "id": "0e7edf",
    "string": "* 27 giugno 1836"
  },
  {
    "id": "c1f4af",
    "string": "* [ante ottobre 1836]"
  },
  {
    "id": "fe0cfd",
    "string": "* 7 settembre 1836"
  },
  {
    "id": "715721",
    "string": "* 26 settembre 1836"
  },
  {
    "id": "4cee8f",
    "string": "* 11 ottobre 1836"
  },
  {
    "id": "03c04b",
    "string": "* 30 dicembre 1836"
  },
  {
    "id": "26dc6f",
    "string": "* [tra novembre e 31 dicembre] 1836"
  },
  {
    "id": "a1d110",
    "string": "* [tra ottobre 1836 e marzo 1837]"
  },
  {
    "id": "5d5317",
    "string": "* 30 marzo 1837"
  },
  {
    "id": "8e2874",
    "string": "* 28 aprile 1837"
  },
  {
    "id": "bf9945",
    "string": "* 17 luglio 1837"
  },
  {
    "id": "139813",
    "string": "* 24 luglio 1837"
  },
  {
    "id": "2c9db7",
    "string": "* 17 ottobre 1837"
  },
  {
    "id": "73f7e0",
    "string": "* 23 novembre 1837"
  },
  {
    "id": "86bbde",
    "string": "* 11 gennaio 1838"
  },
  {
    "id": "720798",
    "string": "* 29 gennaio 1838"
  },
  {
    "id": "676440",
    "string": "* 12 febbraio 1838"
  },
  {
    "id": "f29d8e",
    "string": "* 26 febbraio 1838"
  },
  {
    "id": "ceb7a7",
    "string": "* 16 maggio 1838"
  },
  {
    "id": "2543e1",
    "string": "* 17 novembre 1838"
  },
  {
    "id": "255d91",
    "string": "* 19 novembre 1838"
  },
  {
    "id": "33bbba",
    "string": "* [ante 1839]"
  },
  {
    "id": "75171e",
    "string": "* 18 gennaio 1839"
  },
  {
    "id": "b9854c",
    "string": "* 10 febbraio 1839"
  },
  {
    "id": "231fed",
    "string": "* 27 marzo 1839"
  },
  {
    "id": "e6259e",
    "string": "* 9 aprile 1839"
  },
  {
    "id": "fadff4",
    "string": "* [ante 16 dicembre 1839]"
  },
  {
    "id": "46b5b2",
    "string": "* 17 aprile 1840"
  },
  {
    "id": "fd55d7",
    "string": "* 5 gennaio 1841"
  },
  {
    "id": "c61915",
    "string": "* [tra marzo e giugno 1841]"
  },
  {
    "id": "95af3e",
    "string": "* 3 giugno 1841"
  },
  {
    "id": "bf6fbc",
    "string": "* 7 giugno 1841"
  },
  {
    "id": "11204f",
    "string": "* 12 giugno 1841"
  },
  {
    "id": "2b99b3",
    "string": "* 14 giugno 1841"
  },
  {
    "id": "7bad1b",
    "string": "* 21 giugno 1841"
  },
  {
    "id": "ba6fb0",
    "string": "* 24 giugno 1841"
  },
  {
    "id": "182f47",
    "string": "* 30 giugno 1841"
  },
  {
    "id": "3be1d1",
    "string": "* 15 luglio 1841"
  },
  {
    "id": "392219",
    "string": "* 5 agosto 1841"
  },
  {
    "id": "af688a",
    "string": "* 12 agosto 1841"
  },
  {
    "id": "3e0a8b",
    "string": "* 31 agosto 1841"
  },
  {
    "id": "87c50f",
    "string": "* 20 settembre 1841"
  },
  {
    "id": "341e49",
    "string": "* 30 novembre 1841"
  },
  {
    "id": "9210ee",
    "string": "* 2 dicembre 1841"
  },
  {
    "id": "2e0bc1",
    "string": "* 15 dicembre 1841"
  },
  {
    "id": "6f0ef2",
    "string": "* 20 dicembre 1841"
  },
  {
    "id": "da9d5b",
    "string": "* 27 dicembre 1841"
  },
  {
    "id": "48d22e",
    "string": "* 30 giugno 1842"
  },
  {
    "id": "b257b0",
    "string": "* [ante 11 ottobre 1843]"
  },
  {
    "id": "739166",
    "string": "* 5 aprile 1844"
  },
  {
    "id": "abd76f",
    "string": "* [ante 18 aprile 1844]"
  },
  {
    "id": "8afe24",
    "string": "* 18 aprile 1844"
  },
  {
    "id": "8f3164",
    "string": "* 29 aprile 1844"
  },
  {
    "id": "e2ff2e",
    "string": "* 14 giugno 1844"
  },
  {
    "id": "00be5c",
    "string": "* [tra ottobre e dicembre 1844]"
  },
  {
    "id": "b56bb8",
    "string": "* 23 gennaio 1845"
  },
  {
    "id": "d330a3",
    "string": "* 22 febbraio 1845"
  },
  {
    "id": "2f63fb",
    "string": "* 19 marzo 1845"
  },
  {
    "id": "aa2be3",
    "string": "* [ante 4 settembre 1846]"
  },
  {
    "id": "bcacfe",
    "string": "* 29 maggio 1848"
  },
  {
    "id": "783b6b",
    "string": "* [ante 29 maggio 1838]"
  },
  {
    "id": "c79b37",
    "string": "* 29 maggio 1838"
  },
  {
    "id": "9e035b",
    "string": "* 31 agosto 1838"
  },
  {
    "id": "8bf529",
    "string": "* [ante 1840]"
  },
  {
    "id": "3835bc",
    "string": "* 11 novembre 1840"
  },
  {
    "id": "bb4183",
    "string": "* [ante 1841]"
  },
  {
    "id": "491f3d",
    "string": "* 13 febbraio 1841"
  },
  {
    "id": "4904d4",
    "string": "* [tra 13 febbraio e 12 maggio 1841]"
  },
  {
    "id": "accba9",
    "string": "* 12 maggio 1841"
  },
  {
    "id": "65c1fe",
    "string": "* 23 giugno 1841"
  },
  {
    "id": "216bbe",
    "string": "* [1843]"
  },
  {
    "id": "009b6a",
    "string": "* 30 ottobre 1846"
  },
  {
    "id": "9b3d0c",
    "string": "* [tra 30 marzo 1850"
  },
  {
    "id": "a51389",
    "string": "* [ante 1851]"
  },
  {
    "id": "dffb6e",
    "string": "* [tra 14 aprile e 31 agosto 1851"
  },
  {
    "id": "501e1f",
    "string": "* 5 aprile 1857"
  },
  {
    "id": "a663cd",
    "string": "* 14 Aprile 1857"
  },
  {
    "id": "91b32f",
    "string": "* 21 aprile 1857"
  },
  {
    "id": "3e1d1c",
    "string": "* 6 luglio 1857"
  },
  {
    "id": "a5a930",
    "string": "* 30 settembre 1857"
  },
  {
    "id": "e327b9",
    "string": "* 17 ottobre 1857"
  },
  {
    "id": "906e70",
    "string": "* 26 ottobre 1857"
  },
  {
    "id": "728577",
    "string": "* 2 novembre 1857"
  },
  {
    "id": "b5efaa",
    "string": "* 25 novembre 1857"
  },
  {
    "id": "60af5a",
    "string": "* [senza data], 1857"
  },
  {
    "id": "a037df",
    "string": "* [senza lastra di deposito], 1857"
  },
  {
    "id": "aa3ca6",
    "string": "* 19 febbraio 1858"
  },
  {
    "id": "1466af",
    "string": "* 28 febbraio 1859"
  },
  {
    "id": "65d310",
    "string": "* 15 marzo 1859"
  },
  {
    "id": "75236b",
    "string": "* 19 marzo 1859"
  },
  {
    "id": "071785",
    "string": "Bustelli-Rossi.petizioni.1859.1"
  },
  {
    "id": "ce37f2",
    "string": "Bustelli-Rossi.petizioni.1862.1"
  },
  {
    "id": "da14d4",
    "string": "Bustelli-Rossi.petizioni.1862.2"
  },
  {
    "id": "816836",
    "string": "Bustelli-Rossi.petizioni.1862.3"
  },
  {
    "id": "bc6e8b",
    "string": "Bustelli-Rossi.petizioni.1867.1"
  },
  {
    "id": "4828dd",
    "string": "Bustelli-Rossi.petizioni.1867.2"
  },
  {
    "id": "648b5e",
    "string": "Bustelli-Rossi.petizioni.1867.3"
  },
  {
    "id": "f67979",
    "string": "Bustelli-Rossi.avvisi.1857.1"
  },
  {
    "id": "3d1485",
    "string": "Bustelli-Rossi.avvisi.1857.2"
  },
  {
    "id": "7d8491",
    "string": "Bustelli-Rossi.avvisi.1859.1"
  },
  {
    "id": "052bcc",
    "string": "Bustelli-Rossi.avvisi.1862.1"
  },
  {
    "id": "bb398a",
    "string": "Bustelli-Rossi.avvisi.1862.2"
  },
  {
    "id": "dbc6c9",
    "string": "Bustelli-Rossi.avvisi.1862.3"
  },
  {
    "id": "2d4d74",
    "string": "Bustelli-Rossi.avvisi.1867.1"
  },
  {
    "id": "35f8ba",
    "string": "Bustelli-Rossi.avvisi.1867.2"
  },
  {
    "id": "3ced7c",
    "string": "Carteggio.1826.1"
  },
  {
    "id": "a34acd",
    "string": "Carteggio.1826.2"
  },
  {
    "id": "c1e983",
    "string": "Carteggio.1827.1"
  },
  {
    "id": "525653",
    "string": "Carteggio.1828.1"
  },
  {
    "id": "ba830e",
    "string": "Carteggio.1828.2"
  },
  {
    "id": "f03d54",
    "string": "Carteggio.1831.1"
  },
  {
    "id": "d3f082",
    "string": "Carteggio.1831.2"
  },
  {
    "id": "eff27b",
    "string": "Carteggio.1832.1"
  },
  {
    "id": "75db5b",
    "string": "Carteggio.1832.2"
  },
  {
    "id": "0f76dc",
    "string": "Carteggio.1833.1"
  },
  {
    "id": "1000c4",
    "string": "Carteggio.1833.2"
  },
  {
    "id": "ba321f",
    "string": "Carteggio.1833.3"
  },
  {
    "id": "9d2766",
    "string": "Carteggio.1835.1"
  },
  {
    "id": "2aa33d",
    "string": "Carteggio.1835.2"
  },
  {
    "id": "1f293f",
    "string": "Carteggio.1835.3"
  },
  {
    "id": "06d26d",
    "string": "Carteggio.1836.1"
  },
  {
    "id": "8c6eca",
    "string": "Carteggio.1836.2"
  },
  {
    "id": "bf0b51",
    "string": "Carteggio.1836.3"
  },
  {
    "id": "c7f0c2",
    "string": "Carteggio.1836.4"
  },
  {
    "id": "d614ba",
    "string": "Carteggio.1836.5"
  },
  {
    "id": "4701b1",
    "string": "Carteggio.1836.6"
  },
  {
    "id": "abec96",
    "string": "Carteggio.1836.7"
  },
  {
    "id": "36fa71",
    "string": "Carteggio.1836.8"
  },
  {
    "id": "73a70b",
    "string": "Carteggio.1836.9"
  },
  {
    "id": "670577",
    "string": "Carteggio.1836.10"
  },
  {
    "id": "9e16d3",
    "string": "Carteggio.1837.1"
  },
  {
    "id": "381b54",
    "string": "Carteggio.1837.2"
  },
  {
    "id": "030ef8",
    "string": "Carteggio.1838.1"
  },
  {
    "id": "5e0b14",
    "string": "Carteggio.1838.2"
  },
  {
    "id": "d54bf5",
    "string": "Carteggio.1838.3"
  },
  {
    "id": "7c7c57",
    "string": "Carteggio.1841.1"
  },
  {
    "id": "a5edb1",
    "string": "Carteggio.1841.2"
  },
  {
    "id": "062fed",
    "string": "Carteggio.1841.3"
  },
  {
    "id": "696705",
    "string": "Carteggio.1842.1"
  },
  {
    "id": "957865",
    "string": "Carteggio.1842.2"
  },
  {
    "id": "29a4c7",
    "string": "Carteggio.1842.3"
  },
  {
    "id": "831f8e",
    "string": "Carteggio.1843.1"
  },
  {
    "id": "b5a59d",
    "string": "Carteggio.1843.2"
  },
  {
    "id": "ad5dc5",
    "string": "Carteggio.1843.3"
  },
  {
    "id": "a90365",
    "string": "Carteggio.1844.1"
  },
  {
    "id": "30c5ac",
    "string": "Carteggio.1844.2"
  },
  {
    "id": "bb0624",
    "string": "Carteggio.1844.3"
  },
  {
    "id": "6e48a3",
    "string": "Carteggio.1844.4"
  },
  {
    "id": "362021",
    "string": "Carteggio.1844.5"
  },
  {
    "id": "332343",
    "string": "Carteggio.1847.1"
  },
  {
    "id": "e8470c",
    "string": "Carteggio.1848.1"
  },
  {
    "id": "44bb1e",
    "string": "Carteggio.1848.2"
  },
  {
    "id": "118cc3",
    "string": "Carteggio.1849.1"
  },
  {
    "id": "14a2ba",
    "string": "Carteggio.1849.2"
  },
  {
    "id": "e9256d",
    "string": "Carteggio.1849.3"
  },
  {
    "id": "b3966c",
    "string": "Carteggio.1849.4"
  },
  {
    "id": "81be0d",
    "string": "Carteggio.1849.5"
  },
  {
    "id": "e394f8",
    "string": "Carteggio.1850.1"
  },
  {
    "id": "947aa6",
    "string": "Carteggio.1850.2a"
  },
  {
    "id": "c1d39a",
    "string": "Carteggio.1850.2b"
  },
  {
    "id": "641d74",
    "string": "Carteggio.1852.1"
  },
  {
    "id": "95ac9e",
    "string": "Carteggio.1852.2"
  },
  {
    "id": "3cbb59",
    "string": "Carteggio.1852.3"
  },
  {
    "id": "137392",
    "string": "Carteggio.1852.4"
  },
  {
    "id": "0a1015",
    "string": "Carteggio.1852.5"
  },
  {
    "id": "d6b78c",
    "string": "Carteggio.1852.6"
  },
  {
    "id": "20ebd5",
    "string": "Carteggio.1853.1"
  },
  {
    "id": "3e7481",
    "string": "Carteggio.1853.2"
  },
  {
    "id": "4f7878",
    "string": "Carteggio.1853.3"
  },
  {
    "id": "50132b",
    "string": "Carteggio.1853.4"
  },
  {
    "id": "10b231",
    "string": "Carteggio.1853.5"
  },
  {
    "id": "ded264",
    "string": "Carteggio.1854.1"
  },
  {
    "id": "aee939",
    "string": "Carteggio.1854.2"
  },
  {
    "id": "79b4b9",
    "string": "Carteggio.1855.1"
  },
  {
    "id": "20a769",
    "string": "Carteggio.1855.2"
  },
  {
    "id": "080ffe",
    "string": "Carteggio.1855.3"
  },
  {
    "id": "06b4fc",
    "string": "Carteggio.1855.4"
  },
  {
    "id": "6da710",
    "string": "Carteggio.1858.1"
  },
  {
    "id": "6b3203",
    "string": "Carteggio.1863.1"
  },
  {
    "id": "575262",
    "string": "Documenti.vari.1815.1"
  },
  {
    "id": "d4ba4a",
    "string": "Documenti.vari.1816.1"
  },
  {
    "id": "fb6b40",
    "string": "Documenti.vari.1831.1"
  },
  {
    "id": "e065c5",
    "string": "Documenti.vari.1831.2"
  },
  {
    "id": "097ca4",
    "string": "Documenti.vari.1831.3"
  },
  {
    "id": "02735f",
    "string": "Documenti.vari.1831.4"
  },
  {
    "id": "33825f",
    "string": "Documenti.vari.1833.1"
  },
  {
    "id": "85e49f",
    "string": "Documenti.vari.1835.1"
  },
  {
    "id": "32d1d9",
    "string": "Documenti.vari.1840.1"
  },
  {
    "id": "f08db9",
    "string": "Documenti.vari.1841.1"
  },
  {
    "id": "3542f5",
    "string": "Documenti.vari.1842.1"
  },
  {
    "id": "a1d460",
    "string": "Documenti.vari.1850.1"
  },
  {
    "id": "6eec05",
    "string": "Documenti.vari.1850.2"
  },
  {
    "id": "42f9cb",
    "string": "Documenti.vari.1853.1"
  },
  {
    "id": "d130f5",
    "string": "Documenti.vari.1858.1"
  },
  {
    "id": "d70114",
    "string": "Documenti.vari.1863.1"
  },
  {
    "id": "4c338a",
    "string": "Documenti.vari.1868.1"
  },
  {
    "id": "bc86f9",
    "string": "Documenti.vari.1869.1"
  },
  {
    "id": "2ea278",
    "string": "Documenti.vari.1869.2"
  },
  {
    "id": "12ebf1",
    "string": "Documenti.vari.1870.1"
  },
  {
    "id": "68c9cc",
    "string": "Documenti.vari.1870.2"
  },
  {
    "id": "a9d8e0",
    "string": "Documenti.vari.1883.1"
  },
  {
    "id": "055e16",
    "string": "Documenti.vari.1886.1"
  },
  {
    "id": "a96dca",
    "string": "Documenti.vari.1900.1"
  },
  {
    "id": "91fbf9",
    "string": "Figura 1a"
  },
  {
    "id": "77e8b6",
    "string": "Figura 1b"
  },
  {
    "id": "fe865a",
    "string": "Figura 1c"
  },
  {
    "id": "183a5c",
    "string": "Figura 2a-b-c"
  },
  {
    "id": "691404",
    "string": "Figura 3a-b"
  },
  {
    "id": "f9b8f2",
    "string": "Figura 3c"
  },
  {
    "id": "f022a8",
    "string": "Figura 4"
  },
  {
    "id": "4e948c",
    "string": "Figura 5a-b"
  },
  {
    "id": "10ee88",
    "string": "Figura 6a-b"
  },
  {
    "id": "c0f75b",
    "string": "Figura 6c-d"
  },
  {
    "id": "1951da",
    "string": "Figura 7a-c"
  },
  {
    "id": "176e17",
    "string": "Figura 8a"
  },
  {
    "id": "046d90",
    "string": "Figura 8b"
  },
  {
    "id": "f637bc",
    "string": "Figura 9a"
  },
  {
    "id": "b1e1c5",
    "string": "Figura 9b"
  },
  {
    "id": "eca691",
    "string": "Figura 10a"
  },
  {
    "id": "13f4be",
    "string": "Figura 10b"
  },
  {
    "id": "82db5d",
    "string": "Figura 11a"
  },
  {
    "id": "3da418",
    "string": "Figura 11b"
  },
  {
    "id": "1fde11",
    "string": "Illustrazione 1"
  },
  {
    "id": "2fe3e4",
    "string": "Illustrazione 2"
  },
  {
    "id": "828137",
    "string": "Illustrazione 3"
  },
  {
    "id": "01e0a3",
    "string": "Illustrazione 4a"
  },
  {
    "id": "aa97e5",
    "string": "Illustrazione 4b"
  },
  {
    "id": "4eb18a",
    "string": "Illustrazione 5a"
  },
  {
    "id": "c03a0b",
    "string": "Illustrazione 5b"
  },
  {
    "id": "3061c4",
    "string": "Illustrazione 6a-b"
  },
  {
    "id": "9efcbe",
    "string": "Illustrazione 6c-d"
  },
  {
    "id": "fe062f",
    "string": "Illustrazione 7a"
  },
  {
    "id": "296d01",
    "string": "Illustrazione 7b"
  },
  {
    "id": "c7dfad",
    "string": "Illustrazione 8a"
  },
  {
    "id": "f86afa",
    "string": "Illustrazione 8b"
  },
  {
    "id": "492c5a",
    "string": "Illustrazione 8c-d"
  },
  {
    "id": "b33ab8",
    "string": "Illustrazione 9"
  },
  {
    "id": "66ae96",
    "string": "Illustrazione 10a-b"
  },
  {
    "id": "5e69dc",
    "string": "Illustrazione 11a-b"
  },
  {
    "id": "ebaba0",
    "string": "Illustrazione 12a-c"
  },
  {
    "id": "a54f33",
    "string": "Illustrazione 13"
  },
  {
    "id": "932a85",
    "string": "Illustrazione 14"
  },
  {
    "id": "04c653",
    "string": "Illustrazione 15a-b"
  },
  {
    "id": "fee763",
    "string": "Illustrazione 16"
  },
  {
    "id": "455a31",
    "string": "Illustrazione 17"
  },
  {
    "id": "8ab286",
    "string": "Illustrazione 18a-b"
  },
  {
    "id": "e9e73e",
    "string": "Illustrazione 18c"
  },
  {
    "id": "517c9a",
    "string": "Illustrazione 19a-b"
  },
  {
    "id": "80f20b",
    "string": "Illustrazione 19c-d"
  },
  {
    "id": "ad8f89",
    "string": "Illustrazione 19e"
  },
  {
    "id": "89bccb",
    "string": "Illustrazione 20a-c"
  },
  {
    "id": "b3e438",
    "string": "Illustrazione 21"
  },
  {
    "id": "dbe16e",
    "string": "Illustrazione 22"
  },
  {
    "id": "6a41f7",
    "string": "Illustrazione 23"
  },
  {
    "id": "3af2f1",
    "string": "Illustrazione 24"
  },
  {
    "id": "69dce9",
    "string": "Illustrazione 25a-c"
  },
  {
    "id": "cc124e",
    "string": "Illustrazione 25d-e"
  },
  {
    "id": "1619e5",
    "string": "Illustrazione 26a"
  },
  {
    "id": "465f14",
    "string": "Illustrazione 26b"
  },
  {
    "id": "74bdfc",
    "string": "Illustrazione 26c"
  },
  {
    "id": "bc4f73",
    "string": "Illustrazione 26d"
  },
  {
    "id": "7279c3",
    "string": "Illustrazione 27"
  },
  {
    "id": "31b96a",
    "string": "Illustrazione 28a-b"
  },
  {
    "id": "aba695",
    "string": "Illustrazione 29a-b"
  },
  {
    "id": "be3c3b",
    "string": "Illustrazione 30a-b"
  },
  {
    "id": "c73859",
    "string": "Illustrazione 31"
  },
  {
    "id": "f47914",
    "string": "Illustrazione 32"
  },
  {
    "id": "91d963",
    "string": "Illustrazione 33"
  },
  {
    "id": "67b2b4",
    "string": "Illustrazione 34"
  },
  {
    "id": "2a9430",
    "string": "Illustrazione 35"
  },
  {
    "id": "8901d5",
    "string": "Illustrazione 36a-c"
  },
  {
    "id": "a6e3b0",
    "string": "Illustrazione 37a-b"
  },
  {
    "id": "f04ff5",
    "string": "Pozzi.petizioni.1839.1"
  },
  {
    "id": "ea0307",
    "string": "Pozzi.petizioni.1840.1"
  },
  {
    "id": "97e35d",
    "string": "Pozzi.petizioni.1841.1"
  },
  {
    "id": "d93cd1",
    "string": "Pozzi.petizioni.1842.1"
  },
  {
    "id": "989c58",
    "string": "Pozzi.petizioni.1842.2"
  },
  {
    "id": "017544",
    "string": "Pozzi.petizioni.1842.3"
  },
  {
    "id": "4db264",
    "string": "Pozzi.petizioni.1842.4"
  },
  {
    "id": "2bc30e",
    "string": "Pozzi.petizioni.1842.5"
  },
  {
    "id": "3971ef",
    "string": "Pozzi.petizioni.1842.6"
  },
  {
    "id": "962e81",
    "string": "Pozzi.petizioni.1842.7"
  },
  {
    "id": "5c2844",
    "string": "Pozzi.petizioni.1842.8"
  },
  {
    "id": "92b84c",
    "string": "Pozzi.petizioni.1842.9"
  },
  {
    "id": "ff6f60",
    "string": "Pozzi.petizioni.1842.10"
  },
  {
    "id": "beb9b5",
    "string": "Pozzi.petizioni.1842.11"
  },
  {
    "id": "af7824",
    "string": "Pozzi.petizioni.1842.12"
  },
  {
    "id": "1d33ab",
    "string": "Pozzi.petizioni.1842.13"
  },
  {
    "id": "c1accb",
    "string": "Pozzi.petizioni.1842.14"
  },
  {
    "id": "fba8d4",
    "string": "Pozzi.petizioni.1842.15"
  },
  {
    "id": "48bf5d",
    "string": "Pozzi.petizioni.1842.16"
  },
  {
    "id": "f4ddcd",
    "string": "Pozzi.petizioni.1842.17"
  },
  {
    "id": "0ce9b8",
    "string": "Pozzi.petizioni.1842.18"
  },
  {
    "id": "9d3d8f",
    "string": "Pozzi.petizioni.1842.19"
  },
  {
    "id": "0d6281",
    "string": "Pozzi.petizioni.1842.20"
  },
  {
    "id": "a791fa",
    "string": "Pozzi.petizioni.1842.21"
  },
  {
    "id": "638aad",
    "string": "Pozzi.petizioni.1842.22"
  },
  {
    "id": "bbcb4b",
    "string": "Pozzi.petizioni.1843.1"
  },
  {
    "id": "3a013c",
    "string": "Pozzi.petizioni.1843.2"
  },
  {
    "id": "2fe80f",
    "string": "Pozzi.petizioni.1843.3"
  },
  {
    "id": "9b7d7b",
    "string": "Pozzi.petizioni.1843.4"
  },
  {
    "id": "4381b1",
    "string": "Pozzi.petizioni.1843.5"
  },
  {
    "id": "3507b3",
    "string": "Pozzi.petizioni.1843.6"
  },
  {
    "id": "06ce1a",
    "string": "Pozzi.petizioni.1843.7"
  },
  {
    "id": "3bf2eb",
    "string": "Pozzi.petizioni.1843.8"
  },
  {
    "id": "52ceb1",
    "string": "Pozzi.petizioni.1843.9"
  },
  {
    "id": "4bb157",
    "string": "Pozzi.petizioni.1843.10"
  },
  {
    "id": "4a630c",
    "string": "Pozzi.petizioni.1843.11"
  },
  {
    "id": "930214",
    "string": "Pozzi.petizioni.1843.12"
  },
  {
    "id": "fd815b",
    "string": "Pozzi.petizioni.1843.13"
  },
  {
    "id": "4546a6",
    "string": "Pozzi.petizioni.1843.14"
  },
  {
    "id": "448249",
    "string": "Pozzi.petizioni.1843.15"
  },
  {
    "id": "e14020",
    "string": "Pozzi.petizioni.1843.16"
  },
  {
    "id": "3aeaf1",
    "string": "Pozzi.petizioni.1843.17"
  },
  {
    "id": "5c9a9a",
    "string": "Pozzi.petizioni.1843.18"
  },
  {
    "id": "0f2adc",
    "string": "Pozzi.petizioni.1843.19"
  },
  {
    "id": "97626e",
    "string": "Pozzi.petizioni.1844.1"
  },
  {
    "id": "050c4e",
    "string": "Pozzi.petizioni.1844.2"
  },
  {
    "id": "4d8dae",
    "string": "Pozzi.petizioni.1844.3"
  },
  {
    "id": "d512e1",
    "string": "Pozzi.petizioni.1844.4"
  },
  {
    "id": "5a22c4",
    "string": "Pozzi.petizioni.1844.5"
  },
  {
    "id": "6f514e",
    "string": "Pozzi.petizioni.1844.6"
  },
  {
    "id": "b9f015",
    "string": "Pozzi.petizioni.1844.7"
  },
  {
    "id": "41966c",
    "string": "Pozzi.petizioni.1844.8"
  },
  {
    "id": "8b34e3",
    "string": "Pozzi.petizioni.1845.1"
  },
  {
    "id": "443626",
    "string": "Pozzi.petizioni.1845.2"
  },
  {
    "id": "009752",
    "string": "Pozzi.petizioni.1845.3"
  },
  {
    "id": "8044ad",
    "string": "Pozzi.petizioni.1845.4"
  },
  {
    "id": "a9a3fe",
    "string": "Pozzi.petizioni.1845.5"
  },
  {
    "id": "8a147c",
    "string": "Pozzi.petizioni.1845.6"
  },
  {
    "id": "9375e5",
    "string": "Pozzi.petizioni.1845.7"
  },
  {
    "id": "e4b57b",
    "string": "Pozzi.petizioni.1845.8"
  },
  {
    "id": "2d055d",
    "string": "Pozzi.petizioni.1845.9"
  },
  {
    "id": "ed730d",
    "string": "Pozzi.petizioni.1845.10"
  },
  {
    "id": "40c39f",
    "string": "Pozzi.petizioni.1845.11"
  },
  {
    "id": "3ecf7d",
    "string": "Pozzi.petizioni.1845.12"
  },
  {
    "id": "efdb60",
    "string": "Pozzi.petizioni.1845.13"
  },
  {
    "id": "b7c0d3",
    "string": "Pozzi.petizioni.1846.1"
  },
  {
    "id": "96f286",
    "string": "Pozzi.petizioni.1846.2"
  },
  {
    "id": "45ce85",
    "string": "Pozzi.petizioni.1846.3"
  },
  {
    "id": "b5fd0d",
    "string": "Pozzi.petizioni.1846.4"
  },
  {
    "id": "fcb014",
    "string": "Pozzi.petizioni.1847.1"
  },
  {
    "id": "017839",
    "string": "Pozzi.petizioni.1847.2"
  },
  {
    "id": "52e9c7",
    "string": "Pozzi.petizioni.1847.3"
  },
  {
    "id": "bdf673",
    "string": "Pozzi.petizioni.1847.4"
  },
  {
    "id": "f435a1",
    "string": "Pozzi.petizioni.1847.5"
  },
  {
    "id": "9fe47b",
    "string": "Pozzi.petizioni.1847.6"
  },
  {
    "id": "b5d366",
    "string": "Pozzi.petizioni.1848.1"
  },
  {
    "id": "5995bc",
    "string": "Pozzi.petizioni.1848.2"
  },
  {
    "id": "b093a7",
    "string": "Pozzi.petizioni.1848.3"
  },
  {
    "id": "4b918c",
    "string": "Pozzi.petizioni.1849.1"
  },
  {
    "id": "9ff82b",
    "string": "Pozzi.petizioni.1849.2"
  },
  {
    "id": "16d396",
    "string": "Pozzi.petizioni.1849.3"
  },
  {
    "id": "9c2327",
    "string": "Pozzi.petizioni.1849.4"
  },
  {
    "id": "ba7851",
    "string": "Pozzi.petizioni.1849.5"
  },
  {
    "id": "b14b9c",
    "string": "Pozzi.petizioni.1849.6"
  },
  {
    "id": "fc6092",
    "string": "Pozzi.petizioni.1849.7"
  },
  {
    "id": "b1776a",
    "string": "Pozzi.petizioni.1850.1"
  },
  {
    "id": "f02a37",
    "string": "Pozzi.petizioni.1850.2"
  },
  {
    "id": "a5d581",
    "string": "Pozzi.petizioni.1850.3"
  },
  {
    "id": "9e5060",
    "string": "Pozzi.petizioni.1850.4"
  },
  {
    "id": "1dd109",
    "string": "Pozzi.petizioni.1850.5"
  },
  {
    "id": "11491e",
    "string": "Pozzi.petizioni.1850.6"
  },
  {
    "id": "010dd4",
    "string": "Pozzi.petizioni.1850.7"
  },
  {
    "id": "a6a48a",
    "string": "Pozzi.petizioni.1850.8"
  },
  {
    "id": "ab591e",
    "string": "Pozzi.petizioni.1851.1"
  },
  {
    "id": "78358d",
    "string": "Pozzi.petizioni.1851.2"
  },
  {
    "id": "04dc96",
    "string": "Pozzi.petizioni.1851.3"
  },
  {
    "id": "6c3ec4",
    "string": "Pozzi.petizioni.1851.4"
  },
  {
    "id": "a916fe",
    "string": "Pozzi.petizioni.1851.5"
  },
  {
    "id": "07cbf6",
    "string": "Pozzi.petizioni.1851.6"
  },
  {
    "id": "5b5f3b",
    "string": "Pozzi.petizioni.1851.7"
  },
  {
    "id": "ca645d",
    "string": "Pozzi.petizioni.1851.8"
  },
  {
    "id": "876224",
    "string": "Pozzi.petizioni.1853.1"
  },
  {
    "id": "0094ac",
    "string": "Pozzi.petizioni.1853.2"
  },
  {
    "id": "8049df",
    "string": "Pozzi.petizioni.1853.3"
  },
  {
    "id": "87611e",
    "string": "Pozzi.petizioni.1853.4"
  },
  {
    "id": "b4686b",
    "string": "Pozzi.petizioni.1853.5"
  },
  {
    "id": "a25dae",
    "string": "Pozzi.petizioni.1853.6"
  },
  {
    "id": "0e1507",
    "string": "Pozzi.petizioni.1853.7"
  },
  {
    "id": "a9bc82",
    "string": "Pozzi.petizioni.1855.1"
  },
  {
    "id": "b43639",
    "string": "Pozzi.petizioni.1855.2"
  },
  {
    "id": "0da703",
    "string": "Pozzi.avvisi.1837.1"
  },
  {
    "id": "a987cc",
    "string": "Pozzi.avvisi.1837.2"
  },
  {
    "id": "215d6f",
    "string": "Pozzi.avvisi.1837.3"
  },
  {
    "id": "d16956",
    "string": "Pozzi.avvisi.1837.4"
  },
  {
    "id": "b9bd46",
    "string": "Pozzi.avvisi.1841.1"
  },
  {
    "id": "82a499",
    "string": "Spinelli.petizioni.1840.1"
  },
  {
    "id": "b828cb",
    "string": "Spinelli.petizioni.1840.2"
  },
  {
    "id": "ce3492",
    "string": "Spinelli.petizioni.1845.1"
  },
  {
    "id": "835344",
    "string": "Spinelli.petizioni.1845.2"
  },
  {
    "id": "573682",
    "string": "Spinelli.petizioni.1845.3"
  },
  {
    "id": "dc6ff8",
    "string": "Spinelli.petizioni.1845.4"
  },
  {
    "id": "43cabc",
    "string": "Spinelli.petizioni.1845.5"
  },
  {
    "id": "1192e7",
    "string": "Spinelli.petizioni.1845.6"
  },
  {
    "id": "6b4d24",
    "string": "Spinelli.petizioni.1846.1"
  },
  {
    "id": "ecade2",
    "string": "Spinelli.petizioni.1846.2"
  },
  {
    "id": "6b4765",
    "string": "Spinelli.petizioni.1846.3"
  },
  {
    "id": "00bf52",
    "string": "Spinelli.petizioni.1846.4"
  },
  {
    "id": "f882fa",
    "string": "Spinelli.petizioni.1846.5"
  },
  {
    "id": "a4be7e",
    "string": "Spinelli.petizioni.1846.6"
  },
  {
    "id": "8a9b88",
    "string": "Spinelli.petizioni.1846.7"
  },
  {
    "id": "4e0be0",
    "string": "Spinelli.petizioni.1846.8"
  },
  {
    "id": "fb73ae",
    "string": "Spinelli.petizioni.1846.9"
  },
  {
    "id": "11c816",
    "string": "Spinelli.petizioni.1846.10"
  },
  {
    "id": "152b67",
    "string": "Spinelli.petizioni.1846.11"
  },
  {
    "id": "ed1cc6",
    "string": "Spinelli.petizioni.1846.12"
  },
  {
    "id": "077000",
    "string": "Spinelli.petizioni.1846.13"
  },
  {
    "id": "dcf499",
    "string": "Spinelli.petizioni.1846.14"
  },
  {
    "id": "d34b07",
    "string": "Spinelli.petizioni.1846.15"
  },
  {
    "id": "12882c",
    "string": "Spinelli.petizioni.1846.16"
  },
  {
    "id": "021099",
    "string": "Spinelli.petizioni.1847.1"
  },
  {
    "id": "c164bf",
    "string": "Spinelli.petizioni.1847.2"
  },
  {
    "id": "f3f86d",
    "string": "Spinelli.petizioni.1847.3"
  },
  {
    "id": "d84dea",
    "string": "Spinelli.petizioni.1847.4"
  },
  {
    "id": "cd9b99",
    "string": "Spinelli.petizioni.1847.5"
  },
  {
    "id": "a77c7e",
    "string": "Spinelli.petizioni.1849.1"
  },
  {
    "id": "5c6923",
    "string": "Spinelli.petizioni.1849.2"
  },
  {
    "id": "71be0d",
    "string": "Spinelli.petizioni.1849.3"
  },
  {
    "id": "7db474",
    "string": "Spinelli.petizioni.1849.4"
  },
  {
    "id": "7fc2b6",
    "string": "Spinelli.petizioni.1850.1"
  },
  {
    "id": "f22d58",
    "string": "Spinelli.petizioni.1850.2"
  },
  {
    "id": "f9220e",
    "string": "Spinelli.petizioni.1850.3"
  },
  {
    "id": "5899f3",
    "string": "Spinelli.petizioni.1850.4"
  },
  {
    "id": "c40ddf",
    "string": "Spinelli.petizioni.1850.5"
  },
  {
    "id": "e91067",
    "string": "Spinelli.petizioni.1850.6"
  },
  {
    "id": "bb2aa4",
    "string": "Spinelli.petizioni.1850.7"
  },
  {
    "id": "5dec1c",
    "string": "Spinelli.petizioni.1850.8"
  },
  {
    "id": "d47d7c",
    "string": "Spinelli.petizioni.1850.9"
  },
  {
    "id": "874d18",
    "string": "Spinelli.petizioni.1850.10"
  },
  {
    "id": "c61633",
    "string": "Spinelli.petizioni.1850.11"
  },
  {
    "id": "0bb92f",
    "string": "Spinelli.petizioni.1851.1"
  },
  {
    "id": "a29042",
    "string": "Spinelli.petizioni.1851.2"
  },
  {
    "id": "120b7b",
    "string": "Spinelli.petizioni.1851.3"
  },
  {
    "id": "6c05d4",
    "string": "Spinelli.petizioni.1851.4"
  },
  {
    "id": "e644c7",
    "string": "Spinelli.petizioni.1851.5"
  },
  {
    "id": "4e3f3f",
    "string": "Spinelli.petizioni.1851.6"
  },
  {
    "id": "d74d88",
    "string": "Spinelli.petizioni.1851.7"
  },
  {
    "id": "002e25",
    "string": "Spinelli.petizioni.1851.8"
  },
  {
    "id": "01fb26",
    "string": "Spinelli.petizioni.1851.9"
  },
  {
    "id": "5d7f5f",
    "string": "Spinelli.petizioni.1851.10"
  },
  {
    "id": "57c30c",
    "string": "Spinelli.petizioni.1851.11"
  },
  {
    "id": "a70742",
    "string": "Spinelli.petizioni.1851.12"
  },
  {
    "id": "24ef28",
    "string": "Spinelli.petizioni.1851.13"
  },
  {
    "id": "3815e3",
    "string": "Spinelli.petizioni.1851.14"
  },
  {
    "id": "600709",
    "string": "Spinelli.petizioni.1851.15"
  },
  {
    "id": "06b72f",
    "string": "Spinelli.petizioni.1852.1"
  },
  {
    "id": "f25069",
    "string": "Spinelli.petizioni.1852.2"
  },
  {
    "id": "e1eec5",
    "string": "Spinelli.petizioni.1852.3"
  },
  {
    "id": "ade24a",
    "string": "Spinelli.petizioni.1852.4"
  },
  {
    "id": "ee899e",
    "string": "Spinelli.petizioni.1853.1"
  },
  {
    "id": "e9176e",
    "string": "Spinelli.petizioni.1853.2"
  },
  {
    "id": "e096f2",
    "string": "Spinelli.petizioni.1853.3"
  },
  {
    "id": "f84277",
    "string": "Spinelli.petizioni.1853.4"
  },
  {
    "id": "5c8123",
    "string": "Spinelli.petizioni.1853.5"
  },
  {
    "id": "45da3f",
    "string": "Spinelli.petizioni.1854.1"
  },
  {
    "id": "80d80f",
    "string": "Spinelli.petizioni.1854.2"
  },
  {
    "id": "60afa8",
    "string": "Spinelli.petizioni.1854.3"
  },
  {
    "id": "583001",
    "string": "Spinelli.avvisi.1838.1"
  },
  {
    "id": "fd59c6",
    "string": "Spinelli.avvisi.1838.2"
  },
  {
    "id": "5adc15",
    "string": "Spinelli.avvisi.1840.1"
  },
  {
    "id": "f1355a",
    "string": "Spinelli.avvisi.1840.2"
  },
  {
    "id": "1abdf2",
    "string": "Spinelli.avvisi.1841.1"
  },
  {
    "id": "0c0d69",
    "string": "Spinelli.avvisi.1841.2"
  },
  {
    "id": "1a2ffb",
    "string": "Spinelli.avvisi.1841.3"
  },
  {
    "id": "d6b551",
    "string": "Spinelli.avvisi.1845.1"
  },
  {
    "id": "a53d15",
    "string": "Spinelli.avvisi.1845.2"
  },
  {
    "id": "bff829",
    "string": "Spinelli.avvisi.1845.3"
  },
  {
    "id": "ab5bd6",
    "string": "Spinelli.avvisi.1845.4"
  },
  {
    "id": "ba3113",
    "string": "Spinelli.avvisi.1846.1"
  },
  {
    "id": "9a8bbd",
    "string": "Spinelli.avvisi.1846.2"
  },
  {
    "id": "a3ef79",
    "string": "Spinelli.avvisi.1846.3"
  },
  {
    "id": "7d585f",
    "string": "Spinelli.avvisi.1846.4"
  },
  {
    "id": "470f45",
    "string": "Spinelli.avvisi.1846.5"
  },
  {
    "id": "8afd42",
    "string": "Spinelli.avvisi.1846.6"
  },
  {
    "id": "6d6d7e",
    "string": "Spinelli.avvisi.1846.7"
  },
  {
    "id": "8b923e",
    "string": "Spinelli.avvisi.1847.1"
  },
  {
    "id": "8b124d",
    "string": "Spinelli.avvisi.1847.2"
  },
  {
    "id": "8f6803",
    "string": "Spinelli.avvisi.1849.1"
  },
  {
    "id": "68d18a",
    "string": "Spinelli.avvisi.1849.2"
  },
  {
    "id": "204c42",
    "string": "Spinelli.avvisi.1849.3"
  },
  {
    "id": "d88e5e",
    "string": "Spinelli.avvisi.1849.4"
  },
  {
    "id": "e941f0",
    "string": "Spinelli.avvisi.1850.1"
  },
  {
    "id": "b9c0d8",
    "string": "Spinelli.avvisi.1850.2"
  },
  {
    "id": "50e43e",
    "string": "Spinelli.avvisi.1850.3"
  },
  {
    "id": "69f3c5",
    "string": "Spinelli.avvisi.1850.4"
  },
  {
    "id": "d24722",
    "string": "Spinelli.avvisi.1850.5"
  },
  {
    "id": "8113bb",
    "string": "Spinelli.avvisi.1850.6"
  },
  {
    "id": "0ac861",
    "string": "Spinelli.avvisi.1850.7"
  },
  {
    "id": "b5c452",
    "string": "Spinelli.avvisi.1851.1"
  },
  {
    "id": "d61947",
    "string": "Spinelli.avvisi.1851.2"
  },
  {
    "id": "d3494e",
    "string": "Spinelli.avvisi.1851.3"
  },
  {
    "id": "f08a8a",
    "string": "Spinelli.avvisi.1851.4"
  },
  {
    "id": "55fa03",
    "string": "Spinelli.avvisi.1851.5"
  },
  {
    "id": "beb389",
    "string": "Spinelli.avvisi.1851.6"
  },
  {
    "id": "5f1992",
    "string": "Spinelli.avvisi.1851.7"
  },
  {
    "id": "086081",
    "string": "Spinelli.avvisi.1851.8"
  },
  {
    "id": "45f20d",
    "string": "Spinelli.avvisi.1851.9"
  },
  {
    "id": "75fc7a",
    "string": "Spinelli.avvisi.1852.1"
  },
  {
    "id": "6e3ee0",
    "string": "Spinelli.avvisi.1852.2"
  },
  {
    "id": "b2df46",
    "string": "Spinelli.avvisi.1852.3"
  },
  {
    "id": "6bc097",
    "string": "Spinelli.avvisi.1853.1"
  },
  {
    "id": "632aaf",
    "string": "[ante 19] novembre 1843"
  },
  {
    "id": "fd0940",
    "string": "[ante 19] agosto 1844"
  },
  {
    "id": "f978a7",
    "string": "[11 luglio 1850]"
  },
  {
    "id": "264326",
    "string": "[5] novembre 1849"
  },
  {
    "id": "0c1d82",
    "string": "aprile 1843"
  },
  {
    "id": "fb1ce7",
    "string": "dicembre 1831"
  },
  {
    "id": "074a02",
    "string": "dicembre 1839"
  },
  {
    "id": "620a94",
    "string": "dicembre 1848–febbraio 1849"
  },
  {
    "id": "77d808",
    "string": "estate 1854"
  },
  {
    "id": "fcb806",
    "string": "fine 1835–inizio 1836"
  },
  {
    "id": "1cd2d3",
    "string": "febbraio–luglio 1849"
  },
  {
    "id": "8ca808",
    "string": "febbraio 1853"
  },
  {
    "id": "004034",
    "string": "fine 1868/inizio 1869"
  },
  {
    "id": "104990",
    "string": "gennaio 1831"
  },
  {
    "id": "1a87a5",
    "string": "gennaio–ottobre 1842"
  },
  {
    "id": "edf6f5",
    "string": "gennaio/settembre 1856"
  },
  {
    "id": "b0fd16",
    "string": "gennaio 1858"
  },
  {
    "id": "976ded",
    "string": "inizio–metà 1839"
  },
  {
    "id": "412c2c",
    "string": "luglio 1863"
  },
  {
    "id": "6a0be7",
    "string": "marzo 1832"
  },
  {
    "id": "3bc094",
    "string": "metà 1835"
  },
  {
    "id": "136b09",
    "string": "marzo–ottobre 1848"
  },
  {
    "id": "f73ffb",
    "string": "novembre-dicembre 1852"
  },
  {
    "id": "706faf",
    "string": "settembre 1850"
  }
]